python/obfuscation.py
python/potato.o.py
python/potato.py
python/potatoscript.o.py
python/potatoscript.py
potatoscript-1.0.2.dist-info/METADATA
potatoscript-1.0.2.dist-info/WHEEL
potatoscript-1.0.2.dist-info/top_level.txt
potatoscript-1.0.2.dist-info/RECORD
