Metadata-Version: 2.1
Name: potatoscript
Version: 1.0.2
Summary: A simple library for create python project
Author: potatoscript
Author-email: potatoscript.com@gmail.com
